commonroad_raceline_planner/__init__.py
commonroad_raceline_planner/configuration/__init__.py
commonroad_raceline_planner/configuration/base_config.py
commonroad_raceline_planner/configuration/ftm_config/__init__.py
commonroad_raceline_planner/configuration/ftm_config/computation_config.py
commonroad_raceline_planner/configuration/ftm_config/execution_config.py
commonroad_raceline_planner/configuration/ftm_config/ftm_config.py
commonroad_raceline_planner/configuration/ftm_config/general_config.py
commonroad_raceline_planner/configuration/ftm_config/optimization_config.py
commonroad_raceline_planner/planner/__init__.py
commonroad_raceline_planner/planner/base_planner.py
commonroad_raceline_planner/planner/ftm_planner/__init__.py
commonroad_raceline_planner/planner/ftm_planner/ftm_dto.py
commonroad_raceline_planner/planner/ftm_planner/ftm_mc_planner.py
commonroad_raceline_planner/planner/ftm_planner/ftm_sp_planner.py
commonroad_raceline_planner/planner/ftm_planner/optimization/__init__.py
commonroad_raceline_planner/planner/ftm_planner/optimization/opt_min_curv.py
commonroad_raceline_planner/planner/ftm_planner/optimization/opt_shortest_path.py
commonroad_raceline_planner/planner/ftm_planner/track_processing/__init__.py
commonroad_raceline_planner/planner/ftm_planner/track_processing/base_layer.py
commonroad_raceline_planner/planner/ftm_planner/track_processing/lin_interpol_layer.py
commonroad_raceline_planner/planner/ftm_planner/track_processing/spline_approx_layer.py
commonroad_raceline_planner/planner/ftm_planner/track_processing/track_processing.py
commonroad_raceline_planner/planner/ftm_planner/track_processing/width_inflation_layer.py
commonroad_raceline_planner/planner/ftm_planner/trajectory_planning/__init__.py
commonroad_raceline_planner/planner/ftm_planner/trajectory_planning/angle3pt.py
commonroad_raceline_planner/planner/ftm_planner/trajectory_planning/calc_ax_profile.py
commonroad_raceline_planner-0.1.1.dist-info/LICENSE
commonroad_raceline_planner-0.1.1.dist-info/METADATA
commonroad_raceline_planner-0.1.1.dist-info/WHEEL
commonroad_raceline_planner-0.1.1.dist-info/RECORD
