Metadata-Version: 2.1
Name: commonroad-raceline-planner
Version: 0.1.1
Summary: CommonRoad Raceline Planner Toolbox
License: BSD
Keywords: autonomous,automated,vehicles,driving,motion,planning,racing
Author: Tobias Mascetta
Author-email: tobias.mascetta@tum.de
Requires-Python: >=3.9,<3.12
Classifier: License :: OSI Approved :: BSD License
Classifier: License :: Other/Proprietary License
Classifier: Operating System :: POSIX :: Linux
Classifier: Programming Language :: Python :: 3
Classifier: Programming Language :: Python :: 3.9
Classifier: Programming Language :: Python :: 3.10
Classifier: Programming Language :: Python :: 3.11
Requires-Dist: casadi (<4.0.0)
Requires-Dist: commonroad-io (>=2022.2)
Requires-Dist: cvxpy (>=1.4,<2.0)
Requires-Dist: matplotlib (<3.9)
Requires-Dist: numpy (>=1.17.4,<2.0)
Requires-Dist: quadprog (<=1.0)
